{"robot":"limo_105_3","level":20,"message":"Stopping the exploration: publishing False to explore/resume","timestamp":"2024-10-29, 12:18"}
{"robot":"limo_105_3","level":20,"message":"Goal was canceled. Stopping the robot.","timestamp":"2024-10-29, 12:18"}
{"robot":"limo_105_3","level":30,"message":"[follow_path] [ActionServer] Client requested to cancel the goal. Cancelling.","timestamp":"2024-10-29, 12:18"}
{"robot":"limo_105_3","level":20,"message":"Goal canceled","timestamp":"2024-10-29, 12:18"}
{"robot":"limo_105_3","level":30,"message":"[navigate_to_pose] [ActionServer] Client requested to cancel the goal. Cancelling.","timestamp":"2024-10-29, 12:18"}
{"robot":"limo_105_3","level":20,"message":"Received a 251 X 298 map @ 0.050 m/pix","timestamp":"2024-10-29, 12:18"}
{"robot":"limo_105_3","level":20,"message":"createLaserObject","timestamp":"2024-10-29, 12:18"}
{"robot":"limo_105_3","level":20,"message":"Received a 251 X 298 map @ 0.050 m/pix","timestamp":"2024-10-29, 12:18"}
{"robot":"limo_105_3","level":20,"message":"createLaserObject","timestamp":"2024-10-29, 12:18"}
{"robot":"limo_105_3","level":20,"message":"Received a 251 X 298 map @ 0.050 m/pix","timestamp":"2024-10-29, 12:18"}
{"robot":"limo_105_3","level":20,"message":"createLaserObject","timestamp":"2024-10-29, 12:18"}
{"robot":"limo_105_3","level":20,"message":"Received a 251 X 298 map @ 0.050 m/pix","timestamp":"2024-10-29, 12:18"}
{"robot":"limo_105_3","level":20,"message":"createLaserObject","timestamp":"2024-10-29, 12:18"}
{"robot":"limo_105_3","level":20,"message":"Received a 251 X 298 map @ 0.050 m/pix","timestamp":"2024-10-29, 12:19"}
{"robot":"limo_105_3","level":20,"message":"createLaserObject","timestamp":"2024-10-29, 12:19"}
{"robot":"limo_105_3","level":20,"message":"Received a 251 X 298 map @ 0.050 m/pix","timestamp":"2024-10-29, 12:19"}
{"robot":"limo_105_3","level":20,"message":"createLaserObject","timestamp":"2024-10-29, 12:19"}
{"robot":"limo_105_3","level":20,"message":"Received a 251 X 298 map @ 0.050 m/pix","timestamp":"2024-10-29, 12:19"}
{"robot":"limo_105_3","level":20,"message":"createLaserObject","timestamp":"2024-10-29, 12:19"}
{"robot":"limo_105_3","level":20,"message":"Received a 251 X 298 map @ 0.050 m/pix","timestamp":"2024-10-29, 12:19"}
{"robot":"limo_105_3","level":20,"message":"createLaserObject","timestamp":"2024-10-29, 12:19"}
{"robot":"limo_105_3","level":20,"message":"Received a 251 X 298 map @ 0.050 m/pix","timestamp":"2024-10-29, 12:19"}
{"robot":"limo_105_3","level":20,"message":"createLaserObject","timestamp":"2024-10-29, 12:19"}
{"robot":"limo_105_3","level":20,"message":"Received a 251 X 298 map @ 0.050 m/pix","timestamp":"2024-10-29, 12:19"}
{"robot":"limo_105_3","level":20,"message":"createLaserObject","timestamp":"2024-10-29, 12:19"}
{"robot":"limo_105_3","level":20,"message":"Received a 251 X 298 map @ 0.050 m/pix","timestamp":"2024-10-29, 12:20"}
{"robot":"limo_105_3","level":20,"message":"createLaserObject","timestamp":"2024-10-29, 12:20"}
{"robot":"limo_105_3","level":20,"message":"Identify service called. Playing sound...","timestamp":"2024-10-29, 12:20"}
{"robot":"limo_105_3","level":20,"message":"Received a 251 X 298 map @ 0.050 m/pix","timestamp":"2024-10-29, 12:20"}
{"robot":"limo_105_3","level":20,"message":"createLaserObject","timestamp":"2024-10-29, 12:20"}
{"robot":"limo_105_3","level":20,"message":"Starting the exploration: publishing True to explore/resume","timestamp":"2024-10-29, 12:20"}
